[
  {
    "name": "Chaos Warp",
    "set_name": "Commander's Arsenal",
    "collector_num": "1",
    "illustrator": "Trevor Claxton",
    "types": [
      "Instant"
    ],
    "supertypes": [],
    "subtypes": [],
    "rarity": "Rare",
    "mana_cost": "2R",
    "converted_mana_cost": 3,
    "oracle_text": [
      "The owner of target permanent shuffles it into his or her library, then reveals the top card of his or her library. If it's a permanent card, he or she puts it onto the battlefield."
    ],
    "flavor_text": null,
    "power": null,
    "toughness": null,
    "loyalty": null,
    "multiverse_id": 338441,
    "other_part": null,
    "color_indicator": null
  },
  {
    "name": "Command Tower",
    "set_name": "Commander's Arsenal",
    "collector_num": "2",
    "illustrator": "Adam Paquette",
    "types": [
      "Land"
    ],
    "supertypes": [],
    "subtypes": [],
    "rarity": "Common",
    "mana_cost": null,
    "converted_mana_cost": 0,
    "oracle_text": [
      "{T}: Add to your mana pool one mana of any color in your commander's color identity."
    ],
    "flavor_text": "When defeat is near and guidance is scarce, all eyes look in one direction.",
    "power": null,
    "toughness": null,
    "loyalty": null,
    "multiverse_id": 338442,
    "other_part": null,
    "color_indicator": null
  },
  {
    "name": "Decree of Pain",
    "set_name": "Commander's Arsenal",
    "collector_num": "3",
    "illustrator": "Mathias Kollros",
    "types": [
      "Sorcery"
    ],
    "supertypes": [],
    "subtypes": [],
    "rarity": "Rare",
    "mana_cost": "6BB",
    "converted_mana_cost": 8,
    "oracle_text": [
      "Destroy all creatures. They can't be regenerated. Draw a card for each creature destroyed this way.",
      "Cycling {3}{B}{B} ({3}{B}{B}, Discard this card: Draw a card.)",
      "When you cycle Decree of Pain, all creatures get -2/-2 until end of turn."
    ],
    "flavor_text": null,
    "power": null,
    "toughness": null,
    "loyalty": null,
    "multiverse_id": 338453,
    "other_part": null,
    "color_indicator": null
  },
  {
    "name": "Desertion",
    "set_name": "Commander's Arsenal",
    "collector_num": "4",
    "illustrator": "Richard Kane Ferguson",
    "types": [
      "Instant"
    ],
    "supertypes": [],
    "subtypes": [],
    "rarity": "Rare",
    "mana_cost": "3UU",
    "converted_mana_cost": 5,
    "oracle_text": [
      "Counter target spell. If an artifact or creature spell is countered this way, put that card onto the battlefield under your control instead of into its owner's graveyard."
    ],
    "flavor_text": "First the insult, then the injury.",
    "power": null,
    "toughness": null,
    "loyalty": null,
    "multiverse_id": 338454,
    "other_part": null,
    "color_indicator": null
  },
  {
    "name": "Diaochan, Artful Beauty",
    "set_name": "Commander's Arsenal",
    "collector_num": "5",
    "illustrator": "Miao Aili",
    "types": [
      "Creature"
    ],
    "supertypes": [
      "Legendary"
    ],
    "subtypes": [
      "Human",
      "Advisor"
    ],
    "rarity": "Rare",
    "mana_cost": "3R",
    "converted_mana_cost": 4,
    "oracle_text": [
      "{T}: Destroy target creature of your choice, then destroy target creature of an opponent's choice. Activate this ability only during your turn, before attackers are declared."
    ],
    "flavor_text": null,
    "power": "1",
    "toughness": "1",
    "loyalty": null,
    "multiverse_id": 338449,
    "other_part": null,
    "color_indicator": null
  },
  {
    "name": "Dragonlair Spider",
    "set_name": "Commander's Arsenal",
    "collector_num": "6",
    "illustrator": "Carl Critchlow",
    "types": [
      "Creature"
    ],
    "supertypes": [],
    "subtypes": [
      "Spider"
    ],
    "rarity": "Rare",
    "mana_cost": "2RRGG",
    "converted_mana_cost": 6,
    "oracle_text": [
      "Reach",
      "Whenever an opponent casts a spell, create a 1/1 green Insect creature token."
    ],
    "flavor_text": "Swarms thrive in its nest, feeding on leathery bits of discarded wing.",
    "power": "5",
    "toughness": "6",
    "loyalty": null,
    "multiverse_id": 338446,
    "other_part": null,
    "color_indicator": null
  },
  {
    "name": "Duplicant",
    "set_name": "Commander's Arsenal",
    "collector_num": "7",
    "illustrator": "Marco Nelor",
    "types": [
      "Artifact",
      "Creature"
    ],
    "supertypes": [],
    "subtypes": [
      "Shapeshifter"
    ],
    "rarity": "Rare",
    "mana_cost": "6",
    "converted_mana_cost": 6,
    "oracle_text": [
      "Imprint — When Duplicant enters the battlefield, you may exile target nontoken creature.",
      "As long as a card exiled with Duplicant is a creature card, Duplicant has the power, toughness, and creature types of the last creature card exiled with Duplicant. It's still a Shapeshifter."
    ],
    "flavor_text": null,
    "power": "2",
    "toughness": "4",
    "loyalty": null,
    "multiverse_id": 338451,
    "other_part": null,
    "color_indicator": null
  },
  {
    "name": "Edric, Spymaster of Trest",
    "set_name": "Commander's Arsenal",
    "collector_num": "8",
    "illustrator": "Volkan Baga",
    "types": [
      "Creature"
    ],
    "supertypes": [
      "Legendary"
    ],
    "subtypes": [
      "Elf",
      "Rogue"
    ],
    "rarity": "Rare",
    "mana_cost": "1GU",
    "converted_mana_cost": 3,
    "oracle_text": [
      "Whenever a creature deals combat damage to one of your opponents, its controller may draw a card."
    ],
    "flavor_text": "\"I am not at liberty to reveal my sources, but I can assure you, the price on your head is high.\"",
    "power": "2",
    "toughness": "2",
    "loyalty": null,
    "multiverse_id": 338443,
    "other_part": null,
    "color_indicator": null
  },
  {
    "name": "Kaalia of the Vast",
    "set_name": "Commander's Arsenal",
    "collector_num": "9",
    "illustrator": "Michael Komarck",
    "types": [
      "Creature"
    ],
    "supertypes": [
      "Legendary"
    ],
    "subtypes": [
      "Human",
      "Cleric"
    ],
    "rarity": "Mythic Rare",
    "mana_cost": "1WBR",
    "converted_mana_cost": 4,
    "oracle_text": [
      "Flying",
      "Whenever Kaalia of the Vast attacks an opponent, you may put an Angel, Demon, or Dragon creature card from your hand onto the battlefield tapped and attacking that opponent."
    ],
    "flavor_text": "\"I'll have my revenge if I have to call on every force from above and below.\"",
    "power": "2",
    "toughness": "2",
    "loyalty": null,
    "multiverse_id": 338444,
    "other_part": null,
    "color_indicator": null
  },
  {
    "name": "Loyal Retainers",
    "set_name": "Commander's Arsenal",
    "collector_num": "10",
    "illustrator": "Solomon Au Yeung",
    "types": [
      "Creature"
    ],
    "supertypes": [],
    "subtypes": [
      "Human",
      "Advisor"
    ],
    "rarity": "Uncommon",
    "mana_cost": "2W",
    "converted_mana_cost": 3,
    "oracle_text": [
      "Sacrifice Loyal Retainers: Return target legendary creature card from your graveyard to the battlefield. Activate this ability only during your turn, before attackers are declared."
    ],
    "flavor_text": null,
    "power": "1",
    "toughness": "1",
    "loyalty": null,
    "multiverse_id": 338450,
    "other_part": null,
    "color_indicator": null
  },
  {
    "name": "Maelstrom Wanderer",
    "set_name": "Commander's Arsenal",
    "collector_num": "11",
    "illustrator": "Thomas M. Baxa",
    "types": [
      "Creature"
    ],
    "supertypes": [
      "Legendary"
    ],
    "subtypes": [
      "Elemental"
    ],
    "rarity": "Mythic Rare",
    "mana_cost": "5URG",
    "converted_mana_cost": 8,
    "oracle_text": [
      "Creatures you control have haste.",
      "Cascade, cascade (When you cast this spell, exile cards from the top of your library until you exile a nonland card that costs less. You may cast it without paying its mana cost. Put the exiled cards on the bottom of your library in a random order. Then do it again.)"
    ],
    "flavor_text": null,
    "power": "7",
    "toughness": "5",
    "loyalty": null,
    "multiverse_id": 338447,
    "other_part": null,
    "color_indicator": null
  },
  {
    "name": "The Mimeoplasm",
    "set_name": "Commander's Arsenal",
    "collector_num": "12",
    "illustrator": "Svetlin Velinov",
    "types": [
      "Creature"
    ],
    "supertypes": [
      "Legendary"
    ],
    "subtypes": [
      "Ooze"
    ],
    "rarity": "Mythic Rare",
    "mana_cost": "2GUB",
    "converted_mana_cost": 5,
    "oracle_text": [
      "As The Mimeoplasm enters the battlefield, you may exile two creature cards from graveyards. If you do, it enters the battlefield as a copy of one of those cards with a number of additional +1/+1 counters on it equal to the power of the other card."
    ],
    "flavor_text": null,
    "power": "0",
    "toughness": "0",
    "loyalty": null,
    "multiverse_id": 338445,
    "other_part": null,
    "color_indicator": null
  },
  {
    "name": "Mind's Eye",
    "set_name": "Commander's Arsenal",
    "collector_num": "13",
    "illustrator": "Karl Kopinski",
    "types": [
      "Artifact"
    ],
    "supertypes": [],
    "subtypes": [],
    "rarity": "Rare",
    "mana_cost": "5",
    "converted_mana_cost": 5,
    "oracle_text": [
      "Whenever an opponent draws a card, you may pay {1}. If you do, draw a card."
    ],
    "flavor_text": "\"Ideas drift like petals on the wind. I have only to lift my face to the breeze.\"",
    "power": null,
    "toughness": null,
    "loyalty": null,
    "multiverse_id": 338452,
    "other_part": null,
    "color_indicator": null
  },
  {
    "name": "Mirari's Wake",
    "set_name": "Commander's Arsenal",
    "collector_num": "14",
    "illustrator": "Volkan Baga",
    "types": [
      "Enchantment"
    ],
    "supertypes": [],
    "subtypes": [],
    "rarity": "Rare",
    "mana_cost": "3GW",
    "converted_mana_cost": 5,
    "oracle_text": [
      "Creatures you control get +1/+1.",
      "Whenever you tap a land for mana, add one mana to your mana pool of any type that land produced."
    ],
    "flavor_text": "Even after a false god tore the magic from Dominaria, power still radiated from the Mirari sword that slew her.",
    "power": null,
    "toughness": null,
    "loyalty": null,
    "multiverse_id": 338455,
    "other_part": null,
    "color_indicator": null
  },
  {
    "name": "Rhystic Study",
    "set_name": "Commander's Arsenal",
    "collector_num": "15",
    "illustrator": "Terese Nielsen",
    "types": [
      "Enchantment"
    ],
    "supertypes": [],
    "subtypes": [],
    "rarity": "Common",
    "mana_cost": "2U",
    "converted_mana_cost": 3,
    "oracle_text": [
      "Whenever an opponent casts a spell, you may draw a card unless that player pays {1}."
    ],
    "flavor_text": "Friends teach what you want to know. Enemies teach what you need to know.",
    "power": null,
    "toughness": null,
    "loyalty": null,
    "multiverse_id": 338457,
    "other_part": null,
    "color_indicator": null
  },
  {
    "name": "Scroll Rack",
    "set_name": "Commander's Arsenal",
    "collector_num": "16",
    "illustrator": "Heather Hudson",
    "types": [
      "Artifact"
    ],
    "supertypes": [],
    "subtypes": [],
    "rarity": "Rare",
    "mana_cost": "2",
    "converted_mana_cost": 2,
    "oracle_text": [
      "{1}, {T}: Exile any number of cards from your hand face down. Put that many cards from the top of your library into your hand. Then look at the exiled cards and put them on top of your library in any order."
    ],
    "flavor_text": null,
    "power": null,
    "toughness": null,
    "loyalty": null,
    "multiverse_id": 338458,
    "other_part": null,
    "color_indicator": null
  },
  {
    "name": "Sylvan Library",
    "set_name": "Commander's Arsenal",
    "collector_num": "17",
    "illustrator": "Yeong-Hao Han",
    "types": [
      "Enchantment"
    ],
    "supertypes": [],
    "subtypes": [],
    "rarity": "Rare",
    "mana_cost": "1G",
    "converted_mana_cost": 2,
    "oracle_text": [
      "At the beginning of your draw step, you may draw two additional cards. If you do, choose two cards in your hand drawn this turn. For each of those cards, pay 4 life or put the card on top of your library."
    ],
    "flavor_text": null,
    "power": null,
    "toughness": null,
    "loyalty": null,
    "multiverse_id": 338456,
    "other_part": null,
    "color_indicator": null
  },
  {
    "name": "Vela the Night-Clad",
    "set_name": "Commander's Arsenal",
    "collector_num": "18",
    "illustrator": "Allen Williams",
    "types": [
      "Creature"
    ],
    "supertypes": [
      "Legendary"
    ],
    "subtypes": [
      "Human",
      "Wizard"
    ],
    "rarity": "Mythic Rare",
    "mana_cost": "4UB",
    "converted_mana_cost": 6,
    "oracle_text": [
      "Intimidate (This creature can't be blocked except by artifact creatures and/or creatures that share a color with it.)",
      "Other creatures you control have intimidate.",
      "Whenever Vela the Night-Clad or another creature you control leaves the battlefield, each opponent loses 1 life."
    ],
    "flavor_text": "Vela snuffs out every trace of Krond's reign, leaving pure nightfall in her wake.",
    "power": "4",
    "toughness": "4",
    "loyalty": null,
    "multiverse_id": 338448,
    "other_part": null,
    "color_indicator": null
  }
]
