[
  {
    "name": "Elspeth, Knight-Errant",
    "set_name": "Guilds of Ravnica Mythic Edition",
    "collector_num": "1",
    "illustrator": "Zack Stella",
    "types": [
      "Planeswalker"
    ],
    "supertypes": [
      "Legendary"
    ],
    "subtypes": [
      "Elspeth"
    ],
    "rarity": "Mythic Rare",
    "mana_cost": "2WW",
    "converted_mana_cost": 4,
    "oracle_text": [
      "+1: Create a 1/1 white Soldier creature token.",
      "+1: Target creature gets +3/+3 and gains flying until end of turn.",
      "−8: You get an emblem with \"Artifacts, creatures, enchantments, and lands you control have indestructible.\""
    ],
    "flavor_text": null,
    "power": null,
    "toughness": null,
    "loyalty": "4",
    "multiverse_id": 456589,
    "other_part": null,
    "color_indicator": null
  },
  {
    "name": "Liliana, the Last Hope",
    "set_name": "Guilds of Ravnica Mythic Edition",
    "collector_num": "2",
    "illustrator": "Kieran Yanner",
    "types": [
      "Planeswalker"
    ],
    "supertypes": [
      "Legendary"
    ],
    "subtypes": [
      "Liliana"
    ],
    "rarity": "Mythic Rare",
    "mana_cost": "1BB",
    "converted_mana_cost": 3,
    "oracle_text": [
      "+1: Up to one target creature gets -2/-1 until your next turn.",
      "−2: Put the top two cards of your library into your graveyard, then you may return a creature card from your graveyard to your hand.",
      "−7: You get an emblem with \"At the beginning of your end step, create X 2/2 black Zombie creature tokens, where X is two plus the number of Zombies you control.\""
    ],
    "flavor_text": null,
    "power": null,
    "toughness": null,
    "loyalty": "3",
    "multiverse_id": 456590,
    "other_part": null,
    "color_indicator": null
  },
  {
    "name": "Daretti, Ingenious Iconoclast",
    "set_name": "Guilds of Ravnica Mythic Edition",
    "collector_num": "3",
    "illustrator": "Svetlin Velinov",
    "types": [
      "Planeswalker"
    ],
    "supertypes": [
      "Legendary"
    ],
    "subtypes": [
      "Daretti"
    ],
    "rarity": "Mythic Rare",
    "mana_cost": "1BR",
    "converted_mana_cost": 3,
    "oracle_text": [
      "+1: Create a 1/1 colorless Construct artifact creature token with defender.",
      "−1: You may sacrifice an artifact. If you do, destroy target artifact or creature.",
      "−6: Choose target artifact card in a graveyard or artifact on the battlefield. Create three tokens that are copies of it."
    ],
    "flavor_text": null,
    "power": null,
    "toughness": null,
    "loyalty": "3",
    "multiverse_id": 456591,
    "other_part": null,
    "color_indicator": null
  },
  {
    "name": "Nicol Bolas, Planeswalker",
    "set_name": "Guilds of Ravnica Mythic Edition",
    "collector_num": "4",
    "illustrator": "Slawomir Maniak",
    "types": [
      "Planeswalker"
    ],
    "supertypes": [
      "Legendary"
    ],
    "subtypes": [
      "Bolas"
    ],
    "rarity": "Mythic Rare",
    "mana_cost": "4UBBR",
    "converted_mana_cost": 8,
    "oracle_text": [
      "+3: Destroy target noncreature permanent.",
      "−2: Gain control of target creature.",
      "−9: Nicol Bolas, Planeswalker deals 7 damage to target player or planeswalker. That player or that planeswalker's controller discards seven cards, then sacrifices seven permanents."
    ],
    "flavor_text": null,
    "power": null,
    "toughness": null,
    "loyalty": "5",
    "multiverse_id": 456592,
    "other_part": null,
    "color_indicator": null
  },
  {
    "name": "Ral, Izzet Viceroy",
    "set_name": "Guilds of Ravnica Mythic Edition",
    "collector_num": "5",
    "illustrator": "Daniel Ljunggren",
    "types": [
      "Planeswalker"
    ],
    "supertypes": [
      "Legendary"
    ],
    "subtypes": [
      "Ral"
    ],
    "rarity": "Mythic Rare",
    "mana_cost": "3UR",
    "converted_mana_cost": 5,
    "oracle_text": [
      "+1: Look at the top two cards of your library. Put one of them into your hand and the other into your graveyard.",
      "−3: Ral, Izzet Viceroy deals damage to target creature equal to the total number of instant and sorcery cards you own in exile and in your graveyard.",
      "−8: You get an emblem with \"Whenever you cast an instant or sorcery spell, this emblem deals 4 damage to any target and you draw two cards.\""
    ],
    "flavor_text": null,
    "power": null,
    "toughness": null,
    "loyalty": "5",
    "multiverse_id": 456593,
    "other_part": null,
    "color_indicator": null
  },
  {
    "name": "Teferi, Hero of Dominaria",
    "set_name": "Guilds of Ravnica Mythic Edition",
    "collector_num": "6",
    "illustrator": "Yongjae Choi",
    "types": [
      "Planeswalker"
    ],
    "supertypes": [
      "Legendary"
    ],
    "subtypes": [
      "Teferi"
    ],
    "rarity": "Mythic Rare",
    "mana_cost": "3WU",
    "converted_mana_cost": 5,
    "oracle_text": [
      "+1: Draw a card. At the beginning of the next end step, untap up to two lands.",
      "−3: Put target nonland permanent into its owner's library third from the top.",
      "−8: You get an emblem with \"Whenever you draw a card, exile target permanent an opponent controls.\""
    ],
    "flavor_text": null,
    "power": null,
    "toughness": null,
    "loyalty": "4",
    "multiverse_id": 456594,
    "other_part": null,
    "color_indicator": null
  },
  {
    "name": "Tezzeret, Agent of Bolas",
    "set_name": "Guilds of Ravnica Mythic Edition",
    "collector_num": "7",
    "illustrator": "Aleksi Briclot",
    "types": [
      "Planeswalker"
    ],
    "supertypes": [
      "Legendary"
    ],
    "subtypes": [
      "Tezzeret"
    ],
    "rarity": "Mythic Rare",
    "mana_cost": "2UB",
    "converted_mana_cost": 4,
    "oracle_text": [
      "+1: Look at the top five cards of your library. You may reveal an artifact card from among them and put it into your hand. Put the rest on the bottom of your library in any order.",
      "−1: Target artifact becomes an artifact creature with base power and toughness 5/5.",
      "−4: Target player loses X life and you gain X life, where X is twice the number of artifacts you control."
    ],
    "flavor_text": null,
    "power": null,
    "toughness": null,
    "loyalty": "3",
    "multiverse_id": 456595,
    "other_part": null,
    "color_indicator": null
  },
  {
    "name": "Vraska, Golgari Queen",
    "set_name": "Guilds of Ravnica Mythic Edition",
    "collector_num": "8",
    "illustrator": "Livia Prima",
    "types": [
      "Planeswalker"
    ],
    "supertypes": [
      "Legendary"
    ],
    "subtypes": [
      "Vraska"
    ],
    "rarity": "Mythic Rare",
    "mana_cost": "2BG",
    "converted_mana_cost": 4,
    "oracle_text": [
      "+2: You may sacrifice another permanent. If you do, you gain 1 life and draw a card.",
      "−3: Destroy target nonland permanent with converted mana cost 3 or less.",
      "−9: You get an emblem with \"Whenever a creature you control deals combat damage to a player, that player loses the game.\""
    ],
    "flavor_text": null,
    "power": null,
    "toughness": null,
    "loyalty": "4",
    "multiverse_id": 456596,
    "other_part": null,
    "color_indicator": null
  }
]
