[
  {
    "name": "Austere Command",
    "set_name": "Amonkhet Invocations",
    "collector_num": "1",
    "illustrator": "Richard Wright",
    "types": [
      "Sorcery"
    ],
    "supertypes": [],
    "subtypes": [],
    "rarity": "Special",
    "mana_cost": "4WW",
    "converted_mana_cost": 6,
    "oracle_text": [
      "Choose two —",
      "• Destroy all artifacts.",
      "• Destroy all enchantments.",
      "• Destroy all creatures with converted mana cost 3 or less.",
      "• Destroy all creatures with converted mana cost 4 or greater."
    ],
    "flavor_text": null,
    "power": null,
    "toughness": null,
    "loyalty": null,
    "multiverse_id": 429860,
    "other_part": null,
    "color_indicator": null
  },
  {
    "name": "Aven Mindcensor",
    "set_name": "Amonkhet Invocations",
    "collector_num": "2",
    "illustrator": "Jose Cabrera",
    "types": [
      "Creature"
    ],
    "supertypes": [],
    "subtypes": [
      "Bird",
      "Wizard"
    ],
    "rarity": "Special",
    "mana_cost": "2W",
    "converted_mana_cost": 3,
    "oracle_text": [
      "Flash",
      "Flying",
      "If an opponent would search a library, that player searches the top four cards of that library instead."
    ],
    "flavor_text": null,
    "power": "2",
    "toughness": "1",
    "loyalty": null,
    "multiverse_id": 429861,
    "other_part": null,
    "color_indicator": null
  },
  {
    "name": "Containment Priest",
    "set_name": "Amonkhet Invocations",
    "collector_num": "3",
    "illustrator": "Igor Kieryluk",
    "types": [
      "Creature"
    ],
    "supertypes": [],
    "subtypes": [
      "Human",
      "Cleric"
    ],
    "rarity": "Special",
    "mana_cost": "1W",
    "converted_mana_cost": 2,
    "oracle_text": [
      "Flash",
      "If a nontoken creature would enter the battlefield and it wasn't cast, exile it instead."
    ],
    "flavor_text": null,
    "power": "2",
    "toughness": "2",
    "loyalty": null,
    "multiverse_id": 429862,
    "other_part": null,
    "color_indicator": null
  },
  {
    "name": "Loyal Retainers",
    "set_name": "Amonkhet Invocations",
    "collector_num": "4",
    "illustrator": "Bastien L. Deharme",
    "types": [
      "Creature"
    ],
    "supertypes": [],
    "subtypes": [
      "Human",
      "Advisor"
    ],
    "rarity": "Special",
    "mana_cost": "2W",
    "converted_mana_cost": 3,
    "oracle_text": [
      "Sacrifice Loyal Retainers: Return target legendary creature card from your graveyard to the battlefield. Activate this ability only during your turn, before attackers are declared."
    ],
    "flavor_text": null,
    "power": "1",
    "toughness": "1",
    "loyalty": null,
    "multiverse_id": 429863,
    "other_part": null,
    "color_indicator": null
  },
  {
    "name": "Oketra the True",
    "set_name": "Amonkhet Invocations",
    "collector_num": "5",
    "illustrator": "Bastien L. Deharme",
    "types": [
      "Creature"
    ],
    "supertypes": [
      "Legendary"
    ],
    "subtypes": [
      "God"
    ],
    "rarity": "Special",
    "mana_cost": "3W",
    "converted_mana_cost": 4,
    "oracle_text": [
      "Double strike, indestructible",
      "Oketra the True can't attack or block unless you control at least three other creatures.",
      "{3}{W}: Create a 1/1 white Warrior creature token with vigilance."
    ],
    "flavor_text": null,
    "power": "3",
    "toughness": "6",
    "loyalty": null,
    "multiverse_id": 429864,
    "other_part": null,
    "color_indicator": null
  },
  {
    "name": "Worship",
    "set_name": "Amonkhet Invocations",
    "collector_num": "6",
    "illustrator": "Cliff Childs",
    "types": [
      "Enchantment"
    ],
    "supertypes": [],
    "subtypes": [],
    "rarity": "Special",
    "mana_cost": "3W",
    "converted_mana_cost": 4,
    "oracle_text": [
      "If you control a creature, damage that would reduce your life total to less than 1 reduces it to 1 instead."
    ],
    "flavor_text": null,
    "power": null,
    "toughness": null,
    "loyalty": null,
    "multiverse_id": 429865,
    "other_part": null,
    "color_indicator": null
  },
  {
    "name": "Wrath of God",
    "set_name": "Amonkhet Invocations",
    "collector_num": "7",
    "illustrator": "Titus Lunter",
    "types": [
      "Sorcery"
    ],
    "supertypes": [],
    "subtypes": [],
    "rarity": "Special",
    "mana_cost": "2WW",
    "converted_mana_cost": 4,
    "oracle_text": [
      "Destroy all creatures. They can't be regenerated."
    ],
    "flavor_text": null,
    "power": null,
    "toughness": null,
    "loyalty": null,
    "multiverse_id": 429866,
    "other_part": null,
    "color_indicator": null
  },
  {
    "name": "Consecrated Sphinx",
    "set_name": "Amonkhet Invocations",
    "collector_num": "8",
    "illustrator": "Lius Lasahido",
    "types": [
      "Creature"
    ],
    "supertypes": [],
    "subtypes": [
      "Sphinx"
    ],
    "rarity": "Special",
    "mana_cost": "4UU",
    "converted_mana_cost": 6,
    "oracle_text": [
      "Flying",
      "Whenever an opponent draws a card, you may draw two cards."
    ],
    "flavor_text": null,
    "power": "4",
    "toughness": "6",
    "loyalty": null,
    "multiverse_id": 429867,
    "other_part": null,
    "color_indicator": null
  },
  {
    "name": "Counterbalance",
    "set_name": "Amonkhet Invocations",
    "collector_num": "9",
    "illustrator": "Joseph Meehan",
    "types": [
      "Enchantment"
    ],
    "supertypes": [],
    "subtypes": [],
    "rarity": "Special",
    "mana_cost": "UU",
    "converted_mana_cost": 2,
    "oracle_text": [
      "Whenever an opponent casts a spell, you may reveal the top card of your library. If you do, counter that spell if it has the same converted mana cost as the revealed card."
    ],
    "flavor_text": null,
    "power": null,
    "toughness": null,
    "loyalty": null,
    "multiverse_id": 429868,
    "other_part": null,
    "color_indicator": null
  },
  {
    "name": "Counterspell",
    "set_name": "Amonkhet Invocations",
    "collector_num": "10",
    "illustrator": "Chase Stone",
    "types": [
      "Instant"
    ],
    "supertypes": [],
    "subtypes": [],
    "rarity": "Special",
    "mana_cost": "UU",
    "converted_mana_cost": 2,
    "oracle_text": [
      "Counter target spell."
    ],
    "flavor_text": null,
    "power": null,
    "toughness": null,
    "loyalty": null,
    "multiverse_id": 429869,
    "other_part": null,
    "color_indicator": null
  },
  {
    "name": "Cryptic Command",
    "set_name": "Amonkhet Invocations",
    "collector_num": "11",
    "illustrator": "Richard Wright",
    "types": [
      "Instant"
    ],
    "supertypes": [],
    "subtypes": [],
    "rarity": "Special",
    "mana_cost": "1UUU",
    "converted_mana_cost": 4,
    "oracle_text": [
      "Choose two —",
      "• Counter target spell.",
      "• Return target permanent to its owner's hand.",
      "• Tap all creatures your opponents control.",
      "• Draw a card."
    ],
    "flavor_text": null,
    "power": null,
    "toughness": null,
    "loyalty": null,
    "multiverse_id": 429870,
    "other_part": null,
    "color_indicator": null
  },
  {
    "name": "Daze",
    "set_name": "Amonkhet Invocations",
    "collector_num": "12",
    "illustrator": "Richard Wright",
    "types": [
      "Instant"
    ],
    "supertypes": [],
    "subtypes": [],
    "rarity": "Special",
    "mana_cost": "1U",
    "converted_mana_cost": 2,
    "oracle_text": [
      "You may return an Island you control to its owner's hand rather than pay Daze's mana cost.",
      "Counter target spell unless its controller pays {1}."
    ],
    "flavor_text": null,
    "power": null,
    "toughness": null,
    "loyalty": null,
    "multiverse_id": 429871,
    "other_part": null,
    "color_indicator": null
  },
  {
    "name": "Divert",
    "set_name": "Amonkhet Invocations",
    "collector_num": "13",
    "illustrator": "Igor Kieryluk",
    "types": [
      "Instant"
    ],
    "supertypes": [],
    "subtypes": [],
    "rarity": "Special",
    "mana_cost": "U",
    "converted_mana_cost": 1,
    "oracle_text": [
      "Change the target of target spell with a single target unless that spell's controller pays {2}."
    ],
    "flavor_text": null,
    "power": null,
    "toughness": null,
    "loyalty": null,
    "multiverse_id": 429872,
    "other_part": null,
    "color_indicator": null
  },
  {
    "name": "Force of Will",
    "set_name": "Amonkhet Invocations",
    "collector_num": "14",
    "illustrator": "Jaime Jones",
    "types": [
      "Instant"
    ],
    "supertypes": [],
    "subtypes": [],
    "rarity": "Special",
    "mana_cost": "3UU",
    "converted_mana_cost": 5,
    "oracle_text": [
      "You may pay 1 life and exile a blue card from your hand rather than pay Force of Will's mana cost.",
      "Counter target spell."
    ],
    "flavor_text": null,
    "power": null,
    "toughness": null,
    "loyalty": null,
    "multiverse_id": 429873,
    "other_part": null,
    "color_indicator": null
  },
  {
    "name": "Kefnet the Mindful",
    "set_name": "Amonkhet Invocations",
    "collector_num": "15",
    "illustrator": "Jose Cabrera",
    "types": [
      "Creature"
    ],
    "supertypes": [
      "Legendary"
    ],
    "subtypes": [
      "God"
    ],
    "rarity": "Special",
    "mana_cost": "2U",
    "converted_mana_cost": 3,
    "oracle_text": [
      "Flying, indestructible",
      "Kefnet the Mindful can't attack or block unless you have seven or more cards in hand.",
      "{3}{U}: Draw a card, then you may return a land you control to its owner's hand."
    ],
    "flavor_text": null,
    "power": "5",
    "toughness": "5",
    "loyalty": null,
    "multiverse_id": 429874,
    "other_part": null,
    "color_indicator": null
  },
  {
    "name": "Pact of Negation",
    "set_name": "Amonkhet Invocations",
    "collector_num": "16",
    "illustrator": "Titus Lunter",
    "types": [
      "Instant"
    ],
    "supertypes": [],
    "subtypes": [],
    "rarity": "Special",
    "mana_cost": "0",
    "converted_mana_cost": 0,
    "oracle_text": [
      "Counter target spell.",
      "At the beginning of your next upkeep, pay {3}{U}{U}. If you don't, you lose the game."
    ],
    "flavor_text": null,
    "power": null,
    "toughness": null,
    "loyalty": null,
    "multiverse_id": 429875,
    "other_part": null,
    "color_indicator": "Blue"
  },
  {
    "name": "Spell Pierce",
    "set_name": "Amonkhet Invocations",
    "collector_num": "17",
    "illustrator": "Joseph Meehan",
    "types": [
      "Instant"
    ],
    "supertypes": [],
    "subtypes": [],
    "rarity": "Special",
    "mana_cost": "U",
    "converted_mana_cost": 1,
    "oracle_text": [
      "Counter target noncreature spell unless its controller pays {2}."
    ],
    "flavor_text": null,
    "power": null,
    "toughness": null,
    "loyalty": null,
    "multiverse_id": 429876,
    "other_part": null,
    "color_indicator": null
  },
  {
    "name": "Stifle",
    "set_name": "Amonkhet Invocations",
    "collector_num": "18",
    "illustrator": "Cliff Childs",
    "types": [
      "Instant"
    ],
    "supertypes": [],
    "subtypes": [],
    "rarity": "Special",
    "mana_cost": "U",
    "converted_mana_cost": 1,
    "oracle_text": [
      "Counter target activated or triggered ability. (Mana abilities can't be targeted.)"
    ],
    "flavor_text": null,
    "power": null,
    "toughness": null,
    "loyalty": null,
    "multiverse_id": 429877,
    "other_part": null,
    "color_indicator": null
  },
  {
    "name": "Attrition",
    "set_name": "Amonkhet Invocations",
    "collector_num": "19",
    "illustrator": "Jose Cabrera",
    "types": [
      "Enchantment"
    ],
    "supertypes": [],
    "subtypes": [],
    "rarity": "Special",
    "mana_cost": "1BB",
    "converted_mana_cost": 3,
    "oracle_text": [
      "{B}, Sacrifice a creature: Destroy target nonblack creature."
    ],
    "flavor_text": null,
    "power": null,
    "toughness": null,
    "loyalty": null,
    "multiverse_id": 429878,
    "other_part": null,
    "color_indicator": null
  },
  {
    "name": "Bontu the Glorified",
    "set_name": "Amonkhet Invocations",
    "collector_num": "20",
    "illustrator": "Daniel Ljunggren",
    "types": [
      "Creature"
    ],
    "supertypes": [
      "Legendary"
    ],
    "subtypes": [
      "God"
    ],
    "rarity": "Special",
    "mana_cost": "2B",
    "converted_mana_cost": 3,
    "oracle_text": [
      "Menace, indestructible",
      "Bontu the Glorified can't attack or block unless a creature died under your control this turn.",
      "{1}{B}, Sacrifice another creature: Scry 1. Each opponent loses 1 life and you gain 1 life."
    ],
    "flavor_text": null,
    "power": "4",
    "toughness": "6",
    "loyalty": null,
    "multiverse_id": 429879,
    "other_part": null,
    "color_indicator": null
  },
  {
    "name": "Dark Ritual",
    "set_name": "Amonkhet Invocations",
    "collector_num": "21",
    "illustrator": "Richard Wright",
    "types": [
      "Instant"
    ],
    "supertypes": [],
    "subtypes": [],
    "rarity": "Special",
    "mana_cost": "B",
    "converted_mana_cost": 1,
    "oracle_text": [
      "Add {B}{B}{B} to your mana pool."
    ],
    "flavor_text": null,
    "power": null,
    "toughness": null,
    "loyalty": null,
    "multiverse_id": 429880,
    "other_part": null,
    "color_indicator": null
  },
  {
    "name": "Diabolic Intent",
    "set_name": "Amonkhet Invocations",
    "collector_num": "22",
    "illustrator": "Joseph Meehan",
    "types": [
      "Sorcery"
    ],
    "supertypes": [],
    "subtypes": [],
    "rarity": "Special",
    "mana_cost": "1B",
    "converted_mana_cost": 2,
    "oracle_text": [
      "As an additional cost to cast Diabolic Intent, sacrifice a creature.",
      "Search your library for a card and put that card into your hand. Then shuffle your library."
    ],
    "flavor_text": null,
    "power": null,
    "toughness": null,
    "loyalty": null,
    "multiverse_id": 429881,
    "other_part": null,
    "color_indicator": null
  },
  {
    "name": "Entomb",
    "set_name": "Amonkhet Invocations",
    "collector_num": "23",
    "illustrator": "Eytan Zana",
    "types": [
      "Instant"
    ],
    "supertypes": [],
    "subtypes": [],
    "rarity": "Special",
    "mana_cost": "B",
    "converted_mana_cost": 1,
    "oracle_text": [
      "Search your library for a card and put that card into your graveyard. Then shuffle your library."
    ],
    "flavor_text": null,
    "power": null,
    "toughness": null,
    "loyalty": null,
    "multiverse_id": 429882,
    "other_part": null,
    "color_indicator": null
  },
  {
    "name": "Mind Twist",
    "set_name": "Amonkhet Invocations",
    "collector_num": "24",
    "illustrator": "Igor Kieryluk",
    "types": [
      "Sorcery"
    ],
    "supertypes": [],
    "subtypes": [],
    "rarity": "Special",
    "mana_cost": "XB",
    "converted_mana_cost": 1,
    "oracle_text": [
      "Target player discards X cards at random."
    ],
    "flavor_text": null,
    "power": null,
    "toughness": null,
    "loyalty": null,
    "multiverse_id": 429883,
    "other_part": null,
    "color_indicator": null
  },
  {
    "name": "Aggravated Assault",
    "set_name": "Amonkhet Invocations",
    "collector_num": "25",
    "illustrator": "Greg Opalinski",
    "types": [
      "Enchantment"
    ],
    "supertypes": [],
    "subtypes": [],
    "rarity": "Special",
    "mana_cost": "2R",
    "converted_mana_cost": 3,
    "oracle_text": [
      "{3}{R}{R}: Untap all creatures you control. After this main phase, there is an additional combat phase followed by an additional main phase. Activate this ability only any time you could cast a sorcery."
    ],
    "flavor_text": null,
    "power": null,
    "toughness": null,
    "loyalty": null,
    "multiverse_id": 429884,
    "other_part": null,
    "color_indicator": null
  },
  {
    "name": "Chain Lightning",
    "set_name": "Amonkhet Invocations",
    "collector_num": "26",
    "illustrator": "Igor Kieryluk",
    "types": [
      "Sorcery"
    ],
    "supertypes": [],
    "subtypes": [],
    "rarity": "Special",
    "mana_cost": "R",
    "converted_mana_cost": 1,
    "oracle_text": [
      "Chain Lightning deals 3 damage to target creature or player. Then that player or that creature's controller may pay {R}{R}. If the player does, he or she may copy this spell and may choose a new target for that copy."
    ],
    "flavor_text": null,
    "power": null,
    "toughness": null,
    "loyalty": null,
    "multiverse_id": 429885,
    "other_part": null,
    "color_indicator": null
  },
  {
    "name": "Hazoret the Fervent",
    "set_name": "Amonkhet Invocations",
    "collector_num": "27",
    "illustrator": "Joseph Meehan",
    "types": [
      "Creature"
    ],
    "supertypes": [
      "Legendary"
    ],
    "subtypes": [
      "God"
    ],
    "rarity": "Special",
    "mana_cost": "3R",
    "converted_mana_cost": 4,
    "oracle_text": [
      "Indestructible, haste",
      "Hazoret the Fervent can't attack or block unless you have one or fewer cards in hand.",
      "{2}{R}, Discard a card: Hazoret deals 2 damage to each opponent."
    ],
    "flavor_text": null,
    "power": "5",
    "toughness": "4",
    "loyalty": null,
    "multiverse_id": 429886,
    "other_part": null,
    "color_indicator": null
  },
  {
    "name": "Rhonas the Indomitable",
    "set_name": "Amonkhet Invocations",
    "collector_num": "28",
    "illustrator": "Jack Wang",
    "types": [
      "Creature"
    ],
    "supertypes": [
      "Legendary"
    ],
    "subtypes": [
      "God"
    ],
    "rarity": "Special",
    "mana_cost": "2G",
    "converted_mana_cost": 3,
    "oracle_text": [
      "Deathtouch, indestructible",
      "Rhonas the Indomitable can't attack or block unless you control another creature with power 4 or greater.",
      "{2}{G}: Another target creature gets +2/+0 and gains trample until end of turn."
    ],
    "flavor_text": null,
    "power": "5",
    "toughness": "5",
    "loyalty": null,
    "multiverse_id": 429887,
    "other_part": null,
    "color_indicator": null
  },
  {
    "name": "Maelstrom Pulse",
    "set_name": "Amonkhet Invocations",
    "collector_num": "29",
    "illustrator": "Igor Kieryluk",
    "types": [
      "Sorcery"
    ],
    "supertypes": [],
    "subtypes": [],
    "rarity": "Special",
    "mana_cost": "1BG",
    "converted_mana_cost": 3,
    "oracle_text": [
      "Destroy target nonland permanent and all other permanents with the same name as that permanent."
    ],
    "flavor_text": null,
    "power": null,
    "toughness": null,
    "loyalty": null,
    "multiverse_id": 429888,
    "other_part": null,
    "color_indicator": null
  },
  {
    "name": "Vindicate",
    "set_name": "Amonkhet Invocations",
    "collector_num": "30",
    "illustrator": "Igor Kieryluk",
    "types": [
      "Sorcery"
    ],
    "supertypes": [],
    "subtypes": [],
    "rarity": "Special",
    "mana_cost": "1WB",
    "converted_mana_cost": 3,
    "oracle_text": [
      "Destroy target permanent."
    ],
    "flavor_text": null,
    "power": null,
    "toughness": null,
    "loyalty": null,
    "multiverse_id": 429889,
    "other_part": null,
    "color_indicator": null
  },
  {
    "name": "Armageddon",
    "set_name": "Amonkhet Invocations",
    "collector_num": "31",
    "illustrator": "Florian de Gesincourt",
    "types": [
      "Sorcery"
    ],
    "supertypes": [],
    "subtypes": [],
    "rarity": "Special",
    "mana_cost": "3W",
    "converted_mana_cost": 4,
    "oracle_text": [
      "Destroy all lands."
    ],
    "flavor_text": null,
    "power": null,
    "toughness": null,
    "loyalty": null,
    "multiverse_id": 430666,
    "other_part": null,
    "color_indicator": null
  },
  {
    "name": "Capsize",
    "set_name": "Amonkhet Invocations",
    "collector_num": "32",
    "illustrator": "Cliff Childs",
    "types": [
      "Instant"
    ],
    "supertypes": [],
    "subtypes": [],
    "rarity": "Special",
    "mana_cost": "1UU",
    "converted_mana_cost": 3,
    "oracle_text": [
      "Buyback {3} (You may pay an additional {3} as you cast this spell. If you do, put this card into your hand as it resolves.)",
      "Return target permanent to its owner's hand."
    ],
    "flavor_text": null,
    "power": null,
    "toughness": null,
    "loyalty": null,
    "multiverse_id": 430667,
    "other_part": null,
    "color_indicator": null
  },
  {
    "name": "Forbid",
    "set_name": "Amonkhet Invocations",
    "collector_num": "33",
    "illustrator": "Richard Wright",
    "types": [
      "Instant"
    ],
    "supertypes": [],
    "subtypes": [],
    "rarity": "Special",
    "mana_cost": "1UU",
    "converted_mana_cost": 3,
    "oracle_text": [
      "Buyback—Discard two cards. (You may discard two cards in addition to any other costs as you cast this spell. If you do, put this card into your hand as it resolves.)",
      "Counter target spell."
    ],
    "flavor_text": null,
    "power": null,
    "toughness": null,
    "loyalty": null,
    "multiverse_id": 430668,
    "other_part": null,
    "color_indicator": null
  },
  {
    "name": "Omniscience",
    "set_name": "Amonkhet Invocations",
    "collector_num": "34",
    "illustrator": "Josh Hass",
    "types": [
      "Enchantment"
    ],
    "supertypes": [],
    "subtypes": [],
    "rarity": "Special",
    "mana_cost": "7UUU",
    "converted_mana_cost": 10,
    "oracle_text": [
      "You may cast spells from your hand without paying their mana costs."
    ],
    "flavor_text": null,
    "power": null,
    "toughness": null,
    "loyalty": null,
    "multiverse_id": 430669,
    "other_part": null,
    "color_indicator": null
  },
  {
    "name": "Opposition",
    "set_name": "Amonkhet Invocations",
    "collector_num": "35",
    "illustrator": "Svetlin Velinov",
    "types": [
      "Enchantment"
    ],
    "supertypes": [],
    "subtypes": [],
    "rarity": "Special",
    "mana_cost": "2UU",
    "converted_mana_cost": 4,
    "oracle_text": [
      "Tap an untapped creature you control: Tap target artifact, creature, or land."
    ],
    "flavor_text": null,
    "power": null,
    "toughness": null,
    "loyalty": null,
    "multiverse_id": 430670,
    "other_part": null,
    "color_indicator": null
  },
  {
    "name": "Sunder",
    "set_name": "Amonkhet Invocations",
    "collector_num": "36",
    "illustrator": "Titus Lunter",
    "types": [
      "Instant"
    ],
    "supertypes": [],
    "subtypes": [],
    "rarity": "Special",
    "mana_cost": "3UU",
    "converted_mana_cost": 5,
    "oracle_text": [
      "Return all lands to their owners' hands."
    ],
    "flavor_text": null,
    "power": null,
    "toughness": null,
    "loyalty": null,
    "multiverse_id": 430671,
    "other_part": null,
    "color_indicator": null
  },
  {
    "name": "Threads of Disloyalty",
    "set_name": "Amonkhet Invocations",
    "collector_num": "37",
    "illustrator": "Yongjae Choi",
    "types": [
      "Enchantment"
    ],
    "supertypes": [],
    "subtypes": [
      "Aura"
    ],
    "rarity": "Special",
    "mana_cost": "1UU",
    "converted_mana_cost": 3,
    "oracle_text": [
      "Enchant creature with converted mana cost 2 or less",
      "You control enchanted creature."
    ],
    "flavor_text": null,
    "power": null,
    "toughness": null,
    "loyalty": null,
    "multiverse_id": 430672,
    "other_part": null,
    "color_indicator": null
  },
  {
    "name": "Avatar of Woe",
    "set_name": "Amonkhet Invocations",
    "collector_num": "38",
    "illustrator": "Igor Kieryluk",
    "types": [
      "Creature"
    ],
    "supertypes": [],
    "subtypes": [
      "Avatar"
    ],
    "rarity": "Special",
    "mana_cost": "6BB",
    "converted_mana_cost": 8,
    "oracle_text": [
      "If there are ten or more creature cards total in all graveyards, Avatar of Woe costs {6} less to cast.",
      "Fear (This creature can't be blocked except by artifact creatures and/or black creatures.)",
      "{T}: Destroy target creature. It can't be regenerated."
    ],
    "flavor_text": null,
    "power": "6",
    "toughness": "5",
    "loyalty": null,
    "multiverse_id": 430673,
    "other_part": null,
    "color_indicator": null
  },
  {
    "name": "Damnation",
    "set_name": "Amonkhet Invocations",
    "collector_num": "39",
    "illustrator": "Zack Stella",
    "types": [
      "Sorcery"
    ],
    "supertypes": [],
    "subtypes": [],
    "rarity": "Special",
    "mana_cost": "2BB",
    "converted_mana_cost": 4,
    "oracle_text": [
      "Destroy all creatures. They can't be regenerated."
    ],
    "flavor_text": null,
    "power": null,
    "toughness": null,
    "loyalty": null,
    "multiverse_id": 430674,
    "other_part": null,
    "color_indicator": null
  },
  {
    "name": "Desolation Angel",
    "set_name": "Amonkhet Invocations",
    "collector_num": "40",
    "illustrator": "Bastien L. Deharme",
    "types": [
      "Creature"
    ],
    "supertypes": [],
    "subtypes": [
      "Angel"
    ],
    "rarity": "Special",
    "mana_cost": "3BB",
    "converted_mana_cost": 5,
    "oracle_text": [
      "Kicker {W}{W} (You may pay an additional {W}{W} as you cast this spell.)",
      "Flying",
      "When Desolation Angel enters the battlefield, destroy all lands you control. If it was kicked, destroy all lands instead."
    ],
    "flavor_text": null,
    "power": "5",
    "toughness": "4",
    "loyalty": null,
    "multiverse_id": 430675,
    "other_part": null,
    "color_indicator": null
  },
  {
    "name": "Diabolic Edict",
    "set_name": "Amonkhet Invocations",
    "collector_num": "41",
    "illustrator": "Daarken",
    "types": [
      "Instant"
    ],
    "supertypes": [],
    "subtypes": [],
    "rarity": "Special",
    "mana_cost": "1B",
    "converted_mana_cost": 2,
    "oracle_text": [
      "Target player sacrifices a creature."
    ],
    "flavor_text": null,
    "power": null,
    "toughness": null,
    "loyalty": null,
    "multiverse_id": 430676,
    "other_part": null,
    "color_indicator": null
  },
  {
    "name": "Doomsday",
    "set_name": "Amonkhet Invocations",
    "collector_num": "42",
    "illustrator": "Jaime Jones",
    "types": [
      "Sorcery"
    ],
    "supertypes": [],
    "subtypes": [],
    "rarity": "Special",
    "mana_cost": "BBB",
    "converted_mana_cost": 3,
    "oracle_text": [
      "Search your library and graveyard for five cards and exile the rest. Put the chosen cards on top of your library in any order. You lose half your life, rounded up."
    ],
    "flavor_text": null,
    "power": null,
    "toughness": null,
    "loyalty": null,
    "multiverse_id": 430677,
    "other_part": null,
    "color_indicator": null
  },
  {
    "name": "No Mercy",
    "set_name": "Amonkhet Invocations",
    "collector_num": "43",
    "illustrator": "Jonas De Ro",
    "types": [
      "Enchantment"
    ],
    "supertypes": [],
    "subtypes": [],
    "rarity": "Special",
    "mana_cost": "2BB",
    "converted_mana_cost": 4,
    "oracle_text": [
      "Whenever a creature deals damage to you, destroy it."
    ],
    "flavor_text": null,
    "power": null,
    "toughness": null,
    "loyalty": null,
    "multiverse_id": 430678,
    "other_part": null,
    "color_indicator": null
  },
  {
    "name": "Slaughter Pact",
    "set_name": "Amonkhet Invocations",
    "collector_num": "44",
    "illustrator": "Josh Hass",
    "types": [
      "Instant"
    ],
    "supertypes": [],
    "subtypes": [],
    "rarity": "Special",
    "mana_cost": "0",
    "converted_mana_cost": 0,
    "oracle_text": [
      "Destroy target nonblack creature.",
      "At the beginning of your next upkeep, pay {2}{B}. If you don't, you lose the game."
    ],
    "flavor_text": null,
    "power": null,
    "toughness": null,
    "loyalty": null,
    "multiverse_id": 430679,
    "other_part": null,
    "color_indicator": "Black"
  },
  {
    "name": "Thoughtseize",
    "set_name": "Amonkhet Invocations",
    "collector_num": "45",
    "illustrator": "James Ryman",
    "types": [
      "Sorcery"
    ],
    "supertypes": [],
    "subtypes": [],
    "rarity": "Special",
    "mana_cost": "B",
    "converted_mana_cost": 1,
    "oracle_text": [
      "Target player reveals his or her hand. You choose a nonland card from it. That player discards that card. You lose 2 life."
    ],
    "flavor_text": null,
    "power": null,
    "toughness": null,
    "loyalty": null,
    "multiverse_id": 430680,
    "other_part": null,
    "color_indicator": null
  },
  {
    "name": "Blood Moon",
    "set_name": "Amonkhet Invocations",
    "collector_num": "46",
    "illustrator": "Christine Choi",
    "types": [
      "Enchantment"
    ],
    "supertypes": [],
    "subtypes": [],
    "rarity": "Special",
    "mana_cost": "2R",
    "converted_mana_cost": 3,
    "oracle_text": [
      "Nonbasic lands are Mountains."
    ],
    "flavor_text": null,
    "power": null,
    "toughness": null,
    "loyalty": null,
    "multiverse_id": 430681,
    "other_part": null,
    "color_indicator": null
  },
  {
    "name": "Boil",
    "set_name": "Amonkhet Invocations",
    "collector_num": "47",
    "illustrator": "Philip Straub",
    "types": [
      "Instant"
    ],
    "supertypes": [],
    "subtypes": [],
    "rarity": "Special",
    "mana_cost": "3R",
    "converted_mana_cost": 4,
    "oracle_text": [
      "Destroy all Islands."
    ],
    "flavor_text": null,
    "power": null,
    "toughness": null,
    "loyalty": null,
    "multiverse_id": 430682,
    "other_part": null,
    "color_indicator": null
  },
  {
    "name": "Shatterstorm",
    "set_name": "Amonkhet Invocations",
    "collector_num": "48",
    "illustrator": "Johann Bodin",
    "types": [
      "Sorcery"
    ],
    "supertypes": [],
    "subtypes": [],
    "rarity": "Special",
    "mana_cost": "2RR",
    "converted_mana_cost": 4,
    "oracle_text": [
      "Destroy all artifacts. They can't be regenerated."
    ],
    "flavor_text": null,
    "power": null,
    "toughness": null,
    "loyalty": null,
    "multiverse_id": 430683,
    "other_part": null,
    "color_indicator": null
  },
  {
    "name": "Through the Breach",
    "set_name": "Amonkhet Invocations",
    "collector_num": "49",
    "illustrator": "Darek Zabrocki",
    "types": [
      "Instant"
    ],
    "supertypes": [],
    "subtypes": [
      "Arcane"
    ],
    "rarity": "Special",
    "mana_cost": "4R",
    "converted_mana_cost": 5,
    "oracle_text": [
      "You may put a creature card from your hand onto the battlefield. That creature gains haste. Sacrifice that creature at the beginning of the next end step.",
      "Splice onto Arcane {2}{R}{R} (As you cast an Arcane spell, you may reveal this card from your hand and pay its splice cost. If you do, add this card's effects to that spell.)"
    ],
    "flavor_text": null,
    "power": null,
    "toughness": null,
    "loyalty": null,
    "multiverse_id": 430684,
    "other_part": null,
    "color_indicator": null
  },
  {
    "name": "Choke",
    "set_name": "Amonkhet Invocations",
    "collector_num": "50",
    "illustrator": "Florian de Gesincourt",
    "types": [
      "Enchantment"
    ],
    "supertypes": [],
    "subtypes": [],
    "rarity": "Special",
    "mana_cost": "2G",
    "converted_mana_cost": 3,
    "oracle_text": [
      "Islands don't untap during their controllers' untap steps."
    ],
    "flavor_text": null,
    "power": null,
    "toughness": null,
    "loyalty": null,
    "multiverse_id": 430685,
    "other_part": null,
    "color_indicator": null
  },
  {
    "name": "The Locust God",
    "set_name": "Amonkhet Invocations",
    "collector_num": "51",
    "illustrator": "Grzegorz Rutkowski",
    "types": [
      "Creature"
    ],
    "supertypes": [
      "Legendary"
    ],
    "subtypes": [
      "God"
    ],
    "rarity": "Special",
    "mana_cost": "4UR",
    "converted_mana_cost": 6,
    "oracle_text": [
      "Flying",
      "Whenever you draw a card, create a 1/1 blue and red Insect creature token with flying and haste.",
      "{2}{U}{R}: Draw a card, then discard a card.",
      "When The Locust God dies, return it to its owner's hand at the beginning of the next end step."
    ],
    "flavor_text": null,
    "power": "4",
    "toughness": "4",
    "loyalty": null,
    "multiverse_id": 430686,
    "other_part": null,
    "color_indicator": null
  },
  {
    "name": "Lord of Extinction",
    "set_name": "Amonkhet Invocations",
    "collector_num": "52",
    "illustrator": "Jason A. Engle",
    "types": [
      "Creature"
    ],
    "supertypes": [],
    "subtypes": [
      "Elemental"
    ],
    "rarity": "Special",
    "mana_cost": "3BG",
    "converted_mana_cost": 5,
    "oracle_text": [
      "Lord of Extinction's power and toughness are each equal to the number of cards in all graveyards."
    ],
    "flavor_text": null,
    "power": "*",
    "toughness": "*",
    "loyalty": null,
    "multiverse_id": 430687,
    "other_part": null,
    "color_indicator": null
  },
  {
    "name": "The Scarab God",
    "set_name": "Amonkhet Invocations",
    "collector_num": "53",
    "illustrator": "Grzegorz Rutkowski",
    "types": [
      "Creature"
    ],
    "supertypes": [
      "Legendary"
    ],
    "subtypes": [
      "God"
    ],
    "rarity": "Special",
    "mana_cost": "3UB",
    "converted_mana_cost": 5,
    "oracle_text": [
      "At the beginning of your upkeep, each opponent loses X life and you scry X, where X is the number of Zombies you control.",
      "{2}{U}{B}: Exile target creature card from a graveyard. Create a token that's a copy of it, except it's a 4/4 black Zombie.",
      "When The Scarab God dies, return it to its owner's hand at the beginning of the next end step."
    ],
    "flavor_text": null,
    "power": "5",
    "toughness": "5",
    "loyalty": null,
    "multiverse_id": 430688,
    "other_part": null,
    "color_indicator": null
  },
  {
    "name": "The Scorpion God",
    "set_name": "Amonkhet Invocations",
    "collector_num": "54",
    "illustrator": "Grzegorz Rutkowski",
    "types": [
      "Creature"
    ],
    "supertypes": [
      "Legendary"
    ],
    "subtypes": [
      "God"
    ],
    "rarity": "Special",
    "mana_cost": "3BR",
    "converted_mana_cost": 5,
    "oracle_text": [
      "Whenever a creature with a -1/-1 counter on it dies, draw a card.",
      "{1}{B}{R}: Put a -1/-1 counter on another target creature.",
      "When The Scorpion God dies, return it to its owner's hand at the beginning of the next end step."
    ],
    "flavor_text": null,
    "power": "6",
    "toughness": "5",
    "loyalty": null,
    "multiverse_id": 430689,
    "other_part": null,
    "color_indicator": null
  }
]
